{
    "processors":[{
        "amd":[{
            "ryzen 5":[{
                "3500":[{
                    "gen":"3rd",
                    "cores":"6",
                    "basespeed":"3.6GHz",
                    "turbospeed":"4.1GHz",
                    "cache":"16MB",
                    "price":"11,199"
                }],
                "3600":[{
                    "gen":"3rd",
                    "cores":"6",
                    "basespeed":"3.6GHz",
                    "turbospeed":"4.2GHz",
                    "cache":"35MB",
                    "price":"17,050"
                }],
                "3600X":[{
                    "gen":"3rd ",
                    "cores":"6",
                    "basespeed":"3.8GHz",
                    "turbospeed":"4.4GHz",
                    "cache":"35MB",
                    "price":"20,499"
                }]

            }],
            "ryzen 7":[{
                "3700X":[{
                    "gen":"3rd ",
                    "cores":"8",
                    "basespeed":"3.6GHz",
                    "turbospeed":"4.4GHz",
                    "cache":"36MB",
                    "price":"29,465"
                }],
                "3800X":[{
                    "gen":"3rd ",
                    "cores":"8",
                    "basespeed":"3.9GHz",
                    "turbospeed":"4.5GHz",
                    "cache":"36MB",
                    "price":"33,449"
                }]
            }],
            "ryzen 9":[{
                "3900X":[{
                    "gen":"3rd ",
                    "cores":"12",
                    "basespeed":"3.8GHz",
                    "turbospeed":"4.6GHz",
                    "cache":"70MB",
                    "price":"48,499"
                }]
            }],
            "threadripper":[]

            }],
            "intel":[{
                "i9":[{
                    "gen":"9",
                    "cores":"8",
                    "basespeed":"3.6GHz",
                    "turbospeed":"5.0GHz",
                    "cache":"16MB",
                    "maxmemorysupport":"128GB"
        
                }],
                "i7":[{
                    "8700K":[{
                        "gen":"8",
                        "cores":"6",
                        "basespeed":"3.7GHz",
                        "turbospeed":"4.7GHz",
                        "cache":"12MB",
                        "maxmemorysupport":"64GB",
                        "price":"27,900"
                    }],
                    "8700":[{
                        "gen":"8",
                        "cores":"6",
                        "basespeed":"3.2GHz",
                        "turbospeed":"4.6GHz",
                        "cache":"12MB",
                        "maxmemorysupport":"64GB",
                        "price":"29,900",
                        "Special":"16GB Optane Memory inside"
                    }],
                    "9700K":[{
                        "gen":"9",
                        "cores":"8",
                        "basespeed":"3.9GHz",
                        "turbospeed":"4.9GHz",
                        "cache":"12MB",
                        "maxmemorysupport":"128GB",
                        "price":"30,999"
                    }]
                }],
                "i5":[{
                    "8400":[{
                        "gen":"8",
                        "cores":"6",
                        "basespeed":"2.8GHz",
                        "turbospeed":"4.0GHz",
                        "cache":"9MB",
                        "maxmemorysupport":"64GB",
                        "price":"15,610"
                    }],
                    "9400":[{
                        "gen":"9",
                        "cores":"6",
                        "basespeed":"2.9GHz",
                        "turbospeed":"4.1GHz",
                        "cache":"9MB",
                        "maxmemorysupport":"64GB",
                        "price":"15,999"
                    }],
                    "9400F":[{
                        "gen":"9",
                        "cores":"6",
                        "basespeed":"2.9GHz",
                        "turbospeed":"4.1GHz",
                        "cache":"9MB",
                        "maxmemorysupport":"64GB",
                        "price":"11,750"
                    }],
                    "9600K":[{
                        "gen":"9",
                        "cores":"6",
                        "basespeed":"3.7GHz",
                        "turbospeed":"4.6GHz",
                        "cache":"9MB",
                        "maxmemorysupport":"64GB",
                        "price":"19,999"
                    }]
                }],
                "i3":[{
                    "6100":[{
                        "gen":"6",
                        "cores":"2",
                        "basespeed":"3.7GHz",
                        "cache":"3MB",
                        "maxmemorysupport":"64GB",
                        "price":"9,000"
                    }],
                    "8100":[{
                        "gen":"8",
                        "cores":"4",
                        "basespeed":"3.6GHz",
                        "cache":"6MB",
                        "maxmemorysupport":"64GB",
                        "price":"11,300"
                    }],
                "9100F":[{
                    "gen":"9",
                    "cores":"4",
                    "basespeed":"3.6GHz",
                    "turbospeed":"4.2GHz",
                    "cache":"6MB",
                    "maxmemorysupport":"64GB",
                    "price":"6,610"
                }]
            }]
        }]
    }]

    
}